NiukeKuaixiaoXingyeQiuzhiGonglveDanengPian20212022Fix1/README.md
NiukeKuaixiaoXingyeQiuzhiGonglveDanengPian20212022Fix1/__init__.py
NiukeKuaixiaoXingyeQiuzhiGonglveDanengPian20212022Fix1/__main__.py
NiukeKuaixiaoXingyeQiuzhiGonglveDanengPian20212022Fix1/file.epub
NiukeKuaixiaoXingyeQiuzhiGonglveDanengPian20212022Fix1/index.html
NiukeKuaixiaoXingyeQiuzhiGonglveDanengPian20212022Fix1/css/__init__.py
NiukeKuaixiaoXingyeQiuzhiGonglveDanengPian20212022Fix1/css/annotations.css
NiukeKuaixiaoXingyeQiuzhiGonglveDanengPian20212022Fix1/css/main.css
NiukeKuaixiaoXingyeQiuzhiGonglveDanengPian20212022Fix1/css/normalize.css
NiukeKuaixiaoXingyeQiuzhiGonglveDanengPian20212022Fix1/css/popup.css
NiukeKuaixiaoXingyeQiuzhiGonglveDanengPian20212022Fix1/font/__init__.py
NiukeKuaixiaoXingyeQiuzhiGonglveDanengPian20212022Fix1/font/fontello.eot
NiukeKuaixiaoXingyeQiuzhiGonglveDanengPian20212022Fix1/font/fontello.svg
NiukeKuaixiaoXingyeQiuzhiGonglveDanengPian20212022Fix1/font/fontello.ttf
NiukeKuaixiaoXingyeQiuzhiGonglveDanengPian20212022Fix1/font/fontello.woff
NiukeKuaixiaoXingyeQiuzhiGonglveDanengPian20212022Fix1/img/__init__.py
NiukeKuaixiaoXingyeQiuzhiGonglveDanengPian20212022Fix1/img/annotator-glyph-sprite.png
NiukeKuaixiaoXingyeQiuzhiGonglveDanengPian20212022Fix1/img/annotator-icon-sprite.png
NiukeKuaixiaoXingyeQiuzhiGonglveDanengPian20212022Fix1/img/apple-touch-icon.png
NiukeKuaixiaoXingyeQiuzhiGonglveDanengPian20212022Fix1/img/cancelfullscreen.png
NiukeKuaixiaoXingyeQiuzhiGonglveDanengPian20212022Fix1/img/close.png
NiukeKuaixiaoXingyeQiuzhiGonglveDanengPian20212022Fix1/img/fullscreen.png
NiukeKuaixiaoXingyeQiuzhiGonglveDanengPian20212022Fix1/img/loader.gif
NiukeKuaixiaoXingyeQiuzhiGonglveDanengPian20212022Fix1/img/menu-icon.png
NiukeKuaixiaoXingyeQiuzhiGonglveDanengPian20212022Fix1/img/save.png
NiukeKuaixiaoXingyeQiuzhiGonglveDanengPian20212022Fix1/img/saved.png
NiukeKuaixiaoXingyeQiuzhiGonglveDanengPian20212022Fix1/img/settings-s.png
niuke_kuaixiao_xingye_qiuzhi_gonglve_daneng_pian_2021_2022_fix1-2025.3.25.0.dist-info/METADATA
niuke_kuaixiao_xingye_qiuzhi_gonglve_daneng_pian_2021_2022_fix1-2025.3.25.0.dist-info/WHEEL
niuke_kuaixiao_xingye_qiuzhi_gonglve_daneng_pian_2021_2022_fix1-2025.3.25.0.dist-info/entry_points.txt
niuke_kuaixiao_xingye_qiuzhi_gonglve_daneng_pian_2021_2022_fix1-2025.3.25.0.dist-info/top_level.txt
niuke_kuaixiao_xingye_qiuzhi_gonglve_daneng_pian_2021_2022_fix1-2025.3.25.0.dist-info/RECORD
